MANIFEST.in
README
setup.py
django_email_usernames.egg-info/PKG-INFO
django_email_usernames.egg-info/SOURCES.txt
django_email_usernames.egg-info/dependency_links.txt
django_email_usernames.egg-info/top_level.txt
django_email_usernames.egg-info/zip-safe
email_usernames/__init__.py
email_usernames/backends.py
email_usernames/forms.py
email_usernames/management.py
email_usernames/urls.py
email_usernames/views.py