Metadata-Version: 1.0
Name: django-email-usernames
Version: 1.0
Summary: Piggy back on django-registration and add email-based usernames.
Home-page: http://bitbucket.org/hakanw/django-email-usernames/
Author: hakanw
Author-email: UNKNOWN
License: UNKNOWN
Platform: UNKNOWN
Classifier: Development Status :: 5 - Production/Stable
Classifier: Environment :: Web Environment
Classifier: Framework :: Django
Classifier: Intended Audience :: Developers
Classifier: License :: OSI Approved :: BSD License
Classifier: Operating System :: OS Independent
Classifier: Programming Language :: Python
Classifier: Topic :: Utilities
